lwn2md-0.0.1.dist-info/METADATA
lwn2md-0.0.1.dist-info/WHEEL
lwn2md-0.0.1.dist-info/entry_points.txt
lwn2md-0.0.1.dist-info/licenses/LICENSE
lwn2md/__init__.py
lwn2md/app.py
lwn2md/util.py
lwn2md-0.0.1.dist-info/RECORD
